mcdppy/__init__.py
mcdppy-0.0.1.dist-info/LICENSE
mcdppy-0.0.1.dist-info/METADATA
mcdppy-0.0.1.dist-info/WHEEL
mcdppy-0.0.1.dist-info/top_level.txt
mcdppy-0.0.1.dist-info/RECORD
