Metadata-Version: 2.1
Name: mcdppy
Version: 0.0.1
Summary: Minecraft Datapack Python Library
Author-email: Minsung Kim <spongbob9876@naver.com>
Project-URL: Homepage, https://github.com/McDic/MCDPPY
Classifier: Programming Language :: Python :: 3
Classifier: License :: OSI Approved :: MIT License
Requires-Python: >=3.11
License-File: LICENSE
